fuf/dispatchdict.py
fuf/pat.py
fuf/wrapper.py
fuf/constraints.py
fuf/interop.py
fuf/selfcall.py
fuf/action.py
fuf/__init__.py
fuf-0.6.1.dist-info/top_level.txt
fuf-0.6.1.dist-info/METADATA
fuf-0.6.1.dist-info/RECORD
fuf-0.6.1.dist-info/DESCRIPTION.rst
fuf-0.6.1.dist-info/metadata.json
fuf-0.6.1.dist-info/WHEEL
