Metadata-Version: 2.0
Name: fuf
Version: 0.6.1
Summary: Funced-Up Functions
Home-page: UNKNOWN
Author: Matt Soucy
Author-email: msoucy@csh.rit.edu
License: MIT
Platform: UNKNOWN
Classifier: Development Status :: 4 - Beta
Classifier: Intended Audience :: Developers
Classifier: License :: OSI Approved :: MIT License
Classifier: Operating System :: OS Independent
Classifier: Programming Language :: Python
Classifier: Programming Language :: Python :: 2.7
Classifier: Programming Language :: Python :: 3.3
Requires-Dist: six
